[
  {
    "created_time": "2025-01-14 21:08:00",
    "tid": "demo-post-0001",
    "content": "今天把 QQ 空间历史说说整理成离线网页了，翻旧内容终于不再费劲。",
    "raw_content": "今天把 QQ 空间历史说说整理成离线网页了，翻旧内容终于不再费劲。",
    "source_name": "示例账号",
    "app_name": "网页端",
    "location": "",
    "comment_count": 3,
    "like_count": 18,
    "image_count": 0,
    "image_urls": "",
    "post_url": "https://user.qzone.qq.com/demo-account/mood/demo-post-0001",
    "ugc_right": "",
    "format": "demo",
    "raw_json": "{\"demo\":true,\"index\":1}",
    "downloaded_image_count": 0,
    "downloaded_image_paths": "",
    "download_errors": ""
  },
  {
    "created_time": "2025-01-22 09:42:00",
    "tid": "demo-post-0002",
    "content": "支持导出 JSON、Excel 和本地 HTML，适合做个人备份，也方便后续再分析。",
    "raw_content": "支持导出 JSON、Excel 和本地 HTML，适合做个人备份，也方便后续再分析。",
    "source_name": "示例账号",
    "app_name": "Android",
    "location": "",
    "comment_count": 1,
    "like_count": 12,
    "image_count": 0,
    "image_urls": "",
    "post_url": "https://user.qzone.qq.com/demo-account/mood/demo-post-0002",
    "ugc_right": "",
    "format": "demo",
    "raw_json": "{\"demo\":true,\"index\":2}",
    "downloaded_image_count": 0,
    "downloaded_image_paths": "",
    "download_errors": ""
  },
  {
    "created_time": "2025-02-03 18:30:00",
    "tid": "demo-post-0003",
    "content": "示例页默认按时间排序，也可以切换成旧到新浏览，查资料时会直观很多。",
    "raw_content": "示例页默认按时间排序，也可以切换成旧到新浏览，查资料时会直观很多。",
    "source_name": "示例账号",
    "app_name": "iPhone",
    "location": "上海",
    "comment_count": 5,
    "like_count": 27,
    "image_count": 0,
    "image_urls": "",
    "post_url": "https://user.qzone.qq.com/demo-account/mood/demo-post-0003",
    "ugc_right": "",
    "format": "demo",
    "raw_json": "{\"demo\":true,\"index\":3}",
    "downloaded_image_count": 0,
    "downloaded_image_paths": "",
    "download_errors": ""
  },
  {
    "created_time": "2025-02-15 23:11:00",
    "tid": "demo-post-0004",
    "content": "这个目录里的文件是发布示例，专门用来展示抓取结果格式，不包含真实账号隐私数据。",
    "raw_content": "这个目录里的文件是发布示例，专门用来展示抓取结果格式，不包含真实账号隐私数据。",
    "source_name": "示例账号",
    "app_name": "网页端",
    "location": "",
    "comment_count": 0,
    "like_count": 31,
    "image_count": 0,
    "image_urls": "",
    "post_url": "https://user.qzone.qq.com/demo-account/mood/demo-post-0004",
    "ugc_right": "",
    "format": "demo",
    "raw_json": "{\"demo\":true,\"index\":4}",
    "downloaded_image_count": 0,
    "downloaded_image_paths": "",
    "download_errors": ""
  }
]
